Mama/__init__.py
Mama/admin.py
Mama/cbLLM.py
Mama/chains.py
Mama/config.py
Mama/embedding_factory.py
Mama/train.py
Mama/utils.py
Mama/webscraper.py
mamai-3.5.1.dist-info/licenses/LICENSE
mamai-3.5.1.dist-info/METADATA
mamai-3.5.1.dist-info/WHEEL
mamai-3.5.1.dist-info/top_level.txt
mamai-3.5.1.dist-info/RECORD
