Metadata-Version: 2.4
Name: MaMAI
Version: 3.5.1
Summary: MaMa è un toolkit RAG modulare basato su LangChain per knowledge base locali e interfacce conversazionali.
Home-page: https://github.com/cyberbionik/MaMa
Author: Francesco Bellifemine
Author-email: effebi.co@gmail.com
Project-URL: Source, https://github.com/cyberbionik/MaMa
Project-URL: Tracker, https://github.com/cyberbionik/MaMa/issues
Classifier: Programming Language :: Python :: 3
Classifier: Programming Language :: Python :: 3.10
Classifier: Programming Language :: Python :: 3.11
Classifier: Programming Language :: Python :: 3.12
Classifier: License :: OSI Approved :: MIT License
Classifier: Operating System :: OS Independent
Requires-Python: >=3.10
License-File: LICENSE
Requires-Dist: langchain>=0.3.27
Requires-Dist: langchain-core>=0.3.76
Requires-Dist: langchain-community>=0.3.29
Requires-Dist: langchain-openai>=0.3.33
Requires-Dist: langchain-text-splitters>=0.3.11
Requires-Dist: faiss-cpu>=1.12.0
Requires-Dist: pypdf>=6.0.0
Requires-Dist: flask>=3.0.0
Requires-Dist: beautifulsoup4>=4.13.0
Requires-Dist: urllib3>=2.0.0
Requires-Dist: requests>=2.31.0
Dynamic: author
Dynamic: author-email
Dynamic: classifier
Dynamic: description
Dynamic: description-content-type
Dynamic: home-page
Dynamic: license-file
Dynamic: project-url
Dynamic: requires-dist
Dynamic: requires-python
Dynamic: summary
